druhg/__init__.py
druhg/_druhg_label.pyd
druhg/_druhg_tree.pyd
druhg/druhg_.py
druhg/plots.py
druhg/tests/__init__.py
druhg/tests/test_druhg.py
druhg-1.0.1.dist-info/METADATA
druhg-1.0.1.dist-info/WHEEL
druhg-1.0.1.dist-info/top_level.txt
druhg-1.0.1.dist-info/RECORD
