Metadata-Version: 2.1
Name: druhg
Version: 1.0.1
Summary: Universal clustering based on dialectical materialism
Home-page: https://github.com/artamono/druhg
Maintainer: Pavel "DRUHG" Artamonov
Maintainer-email: druhg.p@gmail.com
License: BSD
Keywords: cluster clustering density hierarchical
Platform: UNKNOWN
Classifier: Development Status :: 4 - Beta
Classifier: Intended Audience :: Science/Research
Classifier: Intended Audience :: Developers
Classifier: License :: OSI Approved
Classifier: Programming Language :: C
Classifier: Programming Language :: Python
Classifier: Topic :: Software Development
Classifier: Topic :: Scientific/Engineering
Classifier: Operating System :: Microsoft :: Windows
Classifier: Operating System :: POSIX
Classifier: Operating System :: Unix
Classifier: Operating System :: MacOS
Classifier: Programming Language :: Python :: 2.7
Classifier: Programming Language :: Python :: 3.4
Requires-Dist: cython (>=0.27)
Requires-Dist: numpy (>=1.9)
Requires-Dist: scipy (>=0.9)
Requires-Dist: scikit-learn (>=0.17)
